je_web_runner/__init__.py
je_web_runner/__main__.py
je_web_runner/element/__init__.py
je_web_runner/element/web_element_wrapper.py
je_web_runner/manager/__init__.py
je_web_runner/manager/webrunner_manager.py
je_web_runner/utils/__init__.py
je_web_runner/utils/assert_value/__init__.py
je_web_runner/utils/assert_value/result_check.py
je_web_runner/utils/callback/__init__.py
je_web_runner/utils/callback/callback_function_executor.py
je_web_runner/utils/exception/__init__.py
je_web_runner/utils/exception/exception_tags.py
je_web_runner/utils/exception/exceptions.py
je_web_runner/utils/executor/__init__.py
je_web_runner/utils/executor/action_executor.py
je_web_runner/utils/file_process/__init__.py
je_web_runner/utils/file_process/get_dir_file_list.py
je_web_runner/utils/generate_report/__init__.py
je_web_runner/utils/generate_report/generate_html_report.py
je_web_runner/utils/generate_report/generate_json_report.py
je_web_runner/utils/generate_report/generate_xml_report.py
je_web_runner/utils/json/__init__.py
je_web_runner/utils/json/json_file/__init__.py
je_web_runner/utils/json/json_file/json_file.py
je_web_runner/utils/json/json_format/__init__.py
je_web_runner/utils/json/json_format/json_process.py
je_web_runner/utils/logging/__init__.py
je_web_runner/utils/logging/loggin_instance.py
je_web_runner/utils/package_manager/__init__.py
je_web_runner/utils/package_manager/package_manager_class.py
je_web_runner/utils/project/__init__.py
je_web_runner/utils/project/create_project_structure.py
je_web_runner/utils/project/template/__init__.py
je_web_runner/utils/project/template/template_executor.py
je_web_runner/utils/project/template/template_keyword.py
je_web_runner/utils/selenium_utils_wrapper/__init__.py
je_web_runner/utils/selenium_utils_wrapper/desired_capabilities/__init__.py
je_web_runner/utils/selenium_utils_wrapper/desired_capabilities/desired_capabilities.py
je_web_runner/utils/selenium_utils_wrapper/keys/__init__.py
je_web_runner-0.0.66.dist-info/licenses/LICENSE
je_web_runner-0.0.66.dist-info/METADATA
je_web_runner-0.0.66.dist-info/WHEEL
je_web_runner-0.0.66.dist-info/top_level.txt
je_web_runner-0.0.66.dist-info/RECORD
